MorganFingerprint/__init__.py
MorganFingerprint/morgan.py
MorganFingerprint-1.20.dist-info/METADATA
MorganFingerprint-1.20.dist-info/WHEEL
MorganFingerprint-1.20.dist-info/entry_points.txt
MorganFingerprint-1.20.dist-info/top_level.txt
MorganFingerprint-1.20.dist-info/RECORD
